CHANGES
LICENSE
MANIFEST.in
README.rst
setup.cfg
setup.py
tox.ini
docs/Makefile
docs/api.rst
docs/conf.py
docs/contributing.rst
docs/index.rst
docs/quickstart.rst
pyramid_cron/__init__.py
pyramid_cron.egg-info/PKG-INFO
pyramid_cron.egg-info/SOURCES.txt
pyramid_cron.egg-info/dependency_links.txt
pyramid_cron.egg-info/not-zip-safe
pyramid_cron.egg-info/requires.txt
pyramid_cron.egg-info/top_level.txt
pyramid_cron/tests/__init__.py
pyramid_cron/tests/test_functional.py
pyramid_cron/tests/test_unit.py