Metadata-Version: 1.1
Name: pyramid-cron
Version: 0.1
Summary: Simple scheduled tasks for Pyramid.
Home-page: http://github.com/cartlogic/pyramid_cron
Author: Scott Torborg
Author-email: scott@cartlogic.com
License: MIT
Keywords: pyramid scheduled tasks cron
Platform: UNKNOWN
Classifier: Development Status :: 2 - Pre-Alpha
Classifier: License :: OSI Approved :: MIT License
Classifier: Programming Language :: Python :: 2
Classifier: Programming Language :: Python :: 2.7
Classifier: Programming Language :: Python :: 3
Classifier: Programming Language :: Python :: 3.3
Classifier: Programming Language :: Python :: 3.4
Classifier: Framework :: Pyramid
